{
  "db_name": "MySQL",
  "query": "SELECT id, created_at, name, owner_id FROM Server WHERE id = ?",
  "describe": {
    "columns": [
      {
        "ordinal": 0,
        "name": "id",
        "type_info": {
          "type": "LongLong",
          "flags": "NOT_NULL | PRIMARY_KEY | UNSIGNED | AUTO_INCREMENT",
          "char_set": 63,
          "max_size": 20
        }
      },
      {
        "ordinal": 1,
        "name": "created_at",
        "type_info": {
          "type": "Timestamp",
          "flags": "NOT_NULL | UNSIGNED | BINARY | TIMESTAMP",
          "char_set": 63,
          "max_size": 19
        }
      },
      {
        "ordinal": 2,
        "name": "name",
        "type_info": {
          "type": "VarString",
          "flags": "NOT_NULL | NO_DEFAULT_VALUE",
          "char_set": 224,
          "max_size": 128
        }
      },
      {
        "ordinal": 3,
        "name": "owner_id",
        "type_info": {
          "type": "LongLong",
          "flags": "NOT_NULL | MULTIPLE_KEY | UNSIGNED | NO_DEFAULT_VALUE",
          "char_set": 63,
          "max_size": 20
        }
      }
    ],
    "parameters": {
      "Right": 1
    },
    "nullable": [
      false,
      false,
      false,
      false
    ]
  },
  "hash": "181f229d243cae535444392f042aa4f73f09bb649650ddd5ba5abee87c9ba3ab"
}
